<?xml version="1.0"?>
<method xmlns:xsi="http://www.w3.org/2001/XMLSchema-instance" xmlns:xsd="http://www.w3.org/2001/XMLSchema" id="fdfdee1e-7e6b-460f-bd2e-b7f8524d8836" lastModifiedUtc="2011-06-23T21:46:35.548166Z" name="OnBeforeInsert" methodType="CrudEvent" actionType="None" returnMode="None">
  <extendedMetaData />
  <ExtendedPropertiesCollection>
    <extendee type="Sage.Platform.Orm.Entities.OrmEntityMethod" />
  </ExtendedPropertiesCollection>
  <parameter />
  <preExecuteTargets />
  <methodTargets>
    <methodTarget id="847130c0-cdd2-4ef4-9105-bb74f3b596d3" lastModifiedUtc="2011-06-23T21:46:34.84505Z" targetType="Sage.Platform.Orm.DefaultCRUDEventHandler, Sage.Platform" targetMethod="OnBeforeInsert" active="true">
      <ExtendedPropertiesCollection>
        <extendee type="Sage.Platform.Orm.Entities.OrmMethodTarget" />
      </ExtendedPropertiesCollection>
    </methodTarget>
  </methodTargets>
  <postExecuteTargets />
  <postFlushTargets />
</method>